{
  "timestamp": "2026-04-16T01:07:25.397Z",
  "eleccion": "presidenciales 2026",
  "nivel": "region_completa",
  "region": {
    "codigo": "180000",
    "nombre": "PASCO"
  },
  "actasactualizadas": null,
  "candidatos": [],
  "provincias": [
    {
      "codigo": "180200",
      "nombre": "DANIEL ALCIDES CARRIÓN",
      "actasactualizadas": null,
      "candidatos": [],
      "distritos": [
        {
          "codigo": "180202",
          "nombre": "CHACAYÁN",
          "actasactualizadas": null,
          "candidatos": []
        },
        {
          "codigo": "180203",
          "nombre": "GOYLLARISQUIZGA",
          "actasactualizadas": null,
          "candidatos": []
        },
        {
          "codigo": "180204",
          "nombre": "PAUCAR",
          "actasactualizadas": null,
          "candidatos": []
        },
        {
          "codigo": "180205",
          "nombre": "SAN PEDRO DE PILLAO",
          "actasactualizadas": null,
          "candidatos": []
        },
        {
          "codigo": "180206",
          "nombre": "SANTA ANA DE TUSI",
          "actasactualizadas": null,
          "candidatos": []
        },
        {
          "codigo": "180207",
          "nombre": "TAPUC",
          "actasactualizadas": null,
          "candidatos": []
        },
        {
          "codigo": "180208",
          "nombre": "VILCABAMBA",
          "actasactualizadas": null,
          "candidatos": []
        },
        {
          "codigo": "180201",
          "nombre": "YANAHUANCA",
          "actasactualizadas": null,
          "candidatos": []
        }
      ]
    },
    {
      "codigo": "180300",
      "nombre": "OXAPAMPA",
      "actasactualizadas": null,
      "candidatos": [],
      "distritos": [
        {
          "codigo": "180302",
          "nombre": "CHONTABAMBA",
          "actasactualizadas": null,
          "candidatos": []
        },
        {
          "codigo": "180308",
          "nombre": "CONSTITUCIÓN",
          "actasactualizadas": null,
          "candidatos": []
        },
        {
          "codigo": "180303",
          "nombre": "HUANCABAMBA",
          "actasactualizadas": null,
          "candidatos": []
        },
        {
          "codigo": "180301",
          "nombre": "OXAPAMPA",
          "actasactualizadas": null,
          "candidatos": []
        },
        {
          "codigo": "180307",
          "nombre": "PALCAZU",
          "actasactualizadas": null,
          "candidatos": []
        },
        {
          "codigo": "180306",
          "nombre": "POZUZO",
          "actasactualizadas": null,
          "candidatos": []
        },
        {
          "codigo": "180304",
          "nombre": "PUERTO BERMÚDEZ",
          "actasactualizadas": null,
          "candidatos": []
        },
        {
          "codigo": "180305",
          "nombre": "VILLA RICA",
          "actasactualizadas": null,
          "candidatos": []
        }
      ]
    },
    {
      "codigo": "180100",
      "nombre": "PASCO",
      "actasactualizadas": null,
      "candidatos": [],
      "distritos": [
        {
          "codigo": "180101",
          "nombre": "CHAUPIMARCA",
          "actasactualizadas": null,
          "candidatos": []
        },
        {
          "codigo": "180103",
          "nombre": "HUACHÓN",
          "actasactualizadas": null,
          "candidatos": []
        },
        {
          "codigo": "180104",
          "nombre": "HUARIACA",
          "actasactualizadas": null,
          "candidatos": []
        },
        {
          "codigo": "180105",
          "nombre": "HUAYLLAY",
          "actasactualizadas": null,
          "candidatos": []
        },
        {
          "codigo": "180106",
          "nombre": "NINACACA",
          "actasactualizadas": null,
          "candidatos": []
        },
        {
          "codigo": "180107",
          "nombre": "PALLANCHACRA",
          "actasactualizadas": null,
          "candidatos": []
        },
        {
          "codigo": "180108",
          "nombre": "PAUCARTAMBO",
          "actasactualizadas": null,
          "candidatos": []
        },
        {
          "codigo": "180109",
          "nombre": "SAN FRANCISCO DE ASÍS DE YARUSYACÁN",
          "actasactualizadas": null,
          "candidatos": []
        },
        {
          "codigo": "180110",
          "nombre": "SIMÓN BOLÍVAR",
          "actasactualizadas": null,
          "candidatos": []
        },
        {
          "codigo": "180111",
          "nombre": "TICLACAYÁN",
          "actasactualizadas": null,
          "candidatos": []
        },
        {
          "codigo": "180112",
          "nombre": "TINYAHUARCO",
          "actasactualizadas": null,
          "candidatos": []
        },
        {
          "codigo": "180113",
          "nombre": "VICCO",
          "actasactualizadas": null,
          "candidatos": []
        },
        {
          "codigo": "180114",
          "nombre": "YANACANCHA",
          "actasactualizadas": null,
          "candidatos": []
        }
      ]
    }
  ],
  "total": []
}